{
    "bank": {
        "native_name": "中国工商银行",
        "english_name": "Industrial and Commercial Bank of China",
        "country": "CN",
        "url": "https://www.icbc.com.cn"
    },
    "cards": [
        {
            "description": "工银灵通卡",
            "bin": [
                622203
            ],
            "card": {
                "type": "Debit",
                "brand": "UnionPay",
                "country": "CN",
                "level": "Standard"
            },
            "source": "Apple Pay",
            "ext": "png"
        },
        {
            "description": "宇宙星座卡普卡校园版·双鱼座",
            "bin": [
                625249
            ],
            "card": {
                "type": "Credit",
                "brand": "UnionPay",
                "country": "CN",
                "level": "Standard"
            },
            "source": "Apple Pay",
            "ext": "png"
        }
    ]
}